{
	"description": "项目配置文件。",
	"setting": {
		"urlCheck": false,
		"es6": true,
		"postcss": true,
		"minified": true,
		"newFeature": true
	},
	"compileType": "miniprogram",
	"libVersion": "1.5.4",
	"appid": "wx812f52591fe47137",
	"projectname": "%E8%8D%A3%E8%8D%AF%E5%9C%A8%E7%BA%BF",
	"condition": {
		"search": {
			"current": -1,
			"list": []
		},
		"conversation": {
			"current": -1,
			"list": []
		},
		"miniprogram": {
			"current": 2,
			"list": [
				{
					"id": 0,
					"name": "账户",
					"pathName": "pages/homePage/account/account",
					"query": ""
				},
				{
					"id": -1,
					"name": "登录",
					"pathName": "pages/loginPage/login/login",
					"query": ""
				},
				{
					"id": 2,
					"name": "myCoupon",
					"pathName": "pages/homePage/account/myCoupon/myCoupon",
					"query": ""
				},
				{
					"id": -1,
					"name": "购物车",
					"pathName": "pages/homePage/shopcart/shopcart",
					"query": ""
				},
				{
					"id": 4,
					"name": "orderCheckout",
					"pathName": "pages/homePage/shopcart/orderCheckout/orderCheckout",
					"query": "blockId=csjvfa5d2qsqzdsn"
				},
				{
					"id": 5,
					"name": "address",
					"pathName": "pages/homePage/account/myAddress/myAddress",
					"query": ""
				},
				{
					"id": 6,
					"name": "editAddress",
					"pathName": "pages/homePage/account/myAddress/editAddress/editAddress",
					"query": "addressId=01ttdafh6wbnwrai"
				},
				{
					"id": -1,
					"name": "addAddress",
					"pathName": "pages/homePage/account/myAddress/editAddress/editAddress",
					"query": ""
				},
				{
					"id": 8,
					"name": "myFavorite",
					"pathName": "pages/homePage/account/myFavorite/myFavorite",
					"query": ""
				},
				{
					"id": 9,
					"name": "selAddress",
					"pathName": "pages/homePage/shopcart/orderCheckout/selectAddress/selectAddress",
					"query": "orderId=csjvfa5d2qsqzdsn"
				}
			]
		}
	}
}